LICENSE
emmett_haml/__init__.py
emmett_haml/__version__.py
emmett_haml/ext.py
emmett_haml-1.0.0.dist-info/LICENSE
emmett_haml-1.0.0.dist-info/WHEEL
emmett_haml-1.0.0.dist-info/METADATA
emmett_haml-1.0.0.dist-info/RECORD
